.streamlit/config.toml
__init__.py
value_dashboard/config/config_demo.toml
value_dashboard/config/config_template.toml
value_dashboard/config/logging_config.yaml
value_dashboard/datalake/df_db_proxy.py
value_dashboard/img/favicon.ico
value_dashboard/img/logo.jpeg
value_dashboard/img/logo.jpg
value_dashboard/img/logo.png
value_dashboard/img/logo2.png
value_dashboard/metrics/clv.py
value_dashboard/metrics/constants.py
value_dashboard/metrics/conversion.py
value_dashboard/metrics/descriptive.py
value_dashboard/metrics/engagement.py
value_dashboard/metrics/experiment.py
value_dashboard/metrics/ml.py
value_dashboard/pages/chat_with_data.py
value_dashboard/pages/clv_analysis.py
value_dashboard/pages/config_gen.py
value_dashboard/pages/data_import.py
value_dashboard/pages/home.py
value_dashboard/pages/ih_analysis.py
value_dashboard/pages/mkt_dashboard.py
value_dashboard/pages/toml_editor.py
value_dashboard/pipeline/datatools.py
value_dashboard/pipeline/holdings.py
value_dashboard/pipeline/ih.py
value_dashboard/reports/__init__.py
value_dashboard/reports/clv_plots.py
value_dashboard/reports/conversion_plots.py
value_dashboard/reports/descriptive_plots.py
value_dashboard/reports/engagement_plots.py
value_dashboard/reports/experiment_plots.py
value_dashboard/reports/model_ml_scores_plots.py
value_dashboard/reports/registry.py
value_dashboard/reports/repdata.py
value_dashboard/reports/shared_plot_utils.py
value_dashboard/utils/cli.py
value_dashboard/utils/config.py
value_dashboard/utils/config_builder.py
value_dashboard/utils/db_utils.py
value_dashboard/utils/file_utils.py
value_dashboard/utils/logger.py
value_dashboard/utils/plotly_utils.py
value_dashboard/utils/polars_utils.py
value_dashboard/utils/py_utils.py
value_dashboard/utils/st_utils.py
value_dashboard/utils/stats.py
value_dashboard/utils/timer.py
vd_app.py
cdhdashboard-0.1.14.dist-info/METADATA
cdhdashboard-0.1.14.dist-info/WHEEL
cdhdashboard-0.1.14.dist-info/entry_points.txt
cdhdashboard-0.1.14.dist-info/licenses/LICENSE
cdhdashboard-0.1.14.dist-info/RECORD
