Metadata-Version: 2.4
Name: cdhdashboard
Version: 0.1.14
Summary: The CDH Value Dashboard Application is an open-source prototype designed to provide customizable metrics and insights for linking marketing actions to business outcomes, such as customer lifetime value (CLV) and conversion rates.
License: MIT
License-File: LICENSE
Author: Grigoriy Sen
Author-email: grigoriy.sen@pega.com
Requires-Python: >3.10,<3.12
Classifier: License :: OSI Approved :: MIT License
Classifier: Programming Language :: Python :: 3
Classifier: Programming Language :: Python :: 3.11
Requires-Dist: datasketches (>=5.2.0,<6.0.0)
Requires-Dist: duckdb (>=1.4.1,<2.0.0)
Requires-Dist: kaleido (>=1.1.0,<2.0.0)
Requires-Dist: lifetimes (>=0.11.3)
Requires-Dist: numpy (>=1.26.4,<2.0.0)
Requires-Dist: pandas (>=2.3.3,<3.0.0)
Requires-Dist: pandasai (>=3.0.0,<4.0.0)
Requires-Dist: pandasai-openai (>=0.1.6,<0.2.0)
Requires-Dist: pillow (>=10.4.0,<11.0.0)
Requires-Dist: plotly (>=6.3.1,<7.0.0)
Requires-Dist: polars (>=1.34.0,<2.0.0)
Requires-Dist: polars-ds (>=0.10.0,<0.11.0)
Requires-Dist: psutil (>=7.1.0,<8.0.0)
Requires-Dist: scikit-learn (>=1.7.2,<2.0.0)
Requires-Dist: scipy (>=1.10.1,<2.0.0)
Requires-Dist: streamlit (>=1.50.0,<2.0.0)
Requires-Dist: streamlit-autorefresh (>=1.0.1,<2.0.0)
Requires-Dist: streamlit-dimensions (>=0.0.1,<0.0.2)
Requires-Dist: streamlit-dynamic-filters (>=0.1.9,<0.2.0)
Requires-Dist: streamlit-option-menu (>=0.4.0,<0.5.0)
Requires-Dist: streamlit-sortables (>=0.3.1,<0.4.0)
Requires-Dist: streamlit-tags (>=1.2.8,<2.0.0)
Requires-Dist: tomlkit (>=0.13.2,<0.14.0)
